LICENSE.txt
MANIFEST.in
README.rst
check_mesos_service.py
discovery_state.py
requirements.txt
setup.py
nagios_mesos_service_check.egg-info/PKG-INFO
nagios_mesos_service_check.egg-info/SOURCES.txt
nagios_mesos_service_check.egg-info/dependency_links.txt
nagios_mesos_service_check.egg-info/requires.txt
nagios_mesos_service_check.egg-info/top_level.txt