Metadata-Version: 1.1
Name: nagios-mesos-service-check
Version: 0.3.0
Summary: A selection of Nagios plugins to monitor services hosted in OpenTable Mesos.
Home-page: https://github.com/opentable/nagios-mesos-service-check
Author: Steven Schlansker
Author-email: sschlansker@opentable.com
License: Apache 2
Platform: UNKNOWN
Classifier: Development Status :: 4 - Beta
Classifier: Environment :: Console
Classifier: Intended Audience :: System Administrators
Classifier: License :: OSI Approved :: Apache Software License
Classifier: Topic :: System :: Monitoring
Classifier: Topic :: System :: Networking :: Monitoring
